armasec/__init__.py
armasec/armasec.py
armasec/exceptions.py
armasec/openid_config_loader.py
armasec/py.typed
armasec/pytest_extension.py
armasec/token_decoder.py
armasec/token_manager.py
armasec/token_payload.py
armasec/token_security.py
armasec/utilities.py
armasec/pluggable/__init__.py
armasec/pluggable/hookspecs.py
armasec/schemas/__init__.py
armasec/schemas/armasec_config.py
armasec/schemas/jwks.py
armasec/schemas/openid_config.py
armasec_cli/auth.py
armasec_cli/cache.py
armasec_cli/client.py
armasec_cli/config.py
armasec_cli/exceptions.py
armasec_cli/format.py
armasec_cli/logging.py
armasec_cli/main.py
armasec_cli/schemas.py
armasec_cli/time_loop.py
armasec-3.0.2.dist-info/METADATA
armasec-3.0.2.dist-info/WHEEL
armasec-3.0.2.dist-info/entry_points.txt
armasec-3.0.2.dist-info/licenses/LICENSE.md
armasec-3.0.2.dist-info/RECORD
