Metadata-Version: 2.4
Name: armasec
Version: 3.0.2
Summary: Injectable FastAPI auth via OIDC
Project-URL: Homepage, https://github.com/omnivector-solutions/armasec
Project-URL: Repository, https://github.com/omnivector-solutions/armasec
Project-URL: Documentation, https://omnivector-solutions.github.io/armasec
Project-URL: Changelog, https://github.com/omnivector-solutions/armasec/blob/main/CHANGELOG.md
Project-URL: Code of Conduct, https://github.com/omnivector-solutions/armasec/blob/main/CONDUCT.md
Project-URL: Contributing, https://github.com/omnivector-solutions/armasec/blob/main/CONTRIBUTING.md
Author-email: Omnivector Engineering Team <info@omnivector.solutions>
License: MIT
License-File: LICENSE.md
Keywords: auth,fastapi,oauth2,oidc,security
Classifier: Development Status :: 5 - Production/Stable
Classifier: Framework :: FastAPI
Classifier: Intended Audience :: Developers
Classifier: License :: OSI Approved :: MIT License
Classifier: Programming Language :: Python :: 3.12
Classifier: Programming Language :: Python :: 3.13
Classifier: Topic :: Internet :: WWW/HTTP
Classifier: Topic :: Security
Classifier: Topic :: Software Development :: Libraries :: Python Modules
Requires-Python: >=3.12
Requires-Dist: auto-name-enum<4,>=3.0.0
Requires-Dist: fastapi<1,>=0.116.2
Requires-Dist: httpx<1,>=0.28.1
Requires-Dist: pluggy<2,>=1.4.0
Requires-Dist: py-buzz<8,>=7.3
Requires-Dist: pydantic<3,>=2.11.9
Requires-Dist: pytest<9,>=6
Requires-Dist: python-jose[cryptography]<4,>=3.2
Requires-Dist: respx<1,>=0.21
Requires-Dist: snick<3,>=2.1
Requires-Dist: typer<1,>=0.12
Provides-Extra: cli
Requires-Dist: loguru<1,>=0.5.3; extra == 'cli'
Requires-Dist: pendulum<4,>=3.0.0; extra == 'cli'
Requires-Dist: pyperclip<2,>=1.8.2; extra == 'cli'
Requires-Dist: rich<15,>=14.1.0; extra == 'cli'
